llm_reka.py
llm_reka-0.1a0.dist-info/LICENSE
llm_reka-0.1a0.dist-info/METADATA
llm_reka-0.1a0.dist-info/WHEEL
llm_reka-0.1a0.dist-info/entry_points.txt
llm_reka-0.1a0.dist-info/top_level.txt
llm_reka-0.1a0.dist-info/RECORD
