Metadata-Version: 2.1
Name: llm-reka
Version: 0.1a0
Summary: Access Reka models via the Reka API
Author: Simon Willison
License: Apache-2.0
Project-URL: Homepage, https://github.com/simonw/llm-reka
Project-URL: Changelog, https://github.com/simonw/llm-reka/releases
Project-URL: Issues, https://github.com/simonw/llm-reka/issues
Project-URL: CI, https://github.com/simonw/llm-reka/actions
Classifier: License :: OSI Approved :: Apache Software License
License-File: LICENSE
Requires-Dist: llm
Requires-Dist: reka-api
Provides-Extra: test
Requires-Dist: pytest ; extra == 'test'
